[
  {
    "id": "1",
    "name": "Learn React",
    "description": "Learn React router"
  },
  {
    "id": "2",
    "name": "Learn Redux",
    "description": "Learn Redux"
  },
  {
    "id": "3",
    "name": "dfgf",
    "description": "sgfg"
  },
  {
    "id": "5",
    "name": "dfgf",
    "description": "sgfg"
  },
  {
    "id": "10",
    "name": "hj",
    "description": "sg"
  },
  {
    "id": "10",
    "name": "hj",
    "description": "sg"
  },
  {
    "id": "10",
    "name": "hj",
    "description": "sg"
  }
]